hdf5view/__init__.py
hdf5view/main.py
hdf5view/mainwindow.py
hdf5view/models.py
hdf5view/views.py
hdf5view/resources/make_demo_hdf5.py
hdf5view/resources/images/dataset.svg
hdf5view/resources/images/folder-open.svg
hdf5view/resources/images/folder.svg
hdf5view/resources/images/hdf5view.ico
hdf5view/resources/images/hdf5view.png
hdf5view/resources/images/hdf5view.svg
hdf5view/resources/images/image.svg
hdf5view/resources/images/plot.svg
hdf5view-0.2.5.dist-info/LICENSE
hdf5view-0.2.5.dist-info/METADATA
hdf5view-0.2.5.dist-info/WHEEL
hdf5view-0.2.5.dist-info/entry_points.txt
hdf5view-0.2.5.dist-info/top_level.txt
hdf5view-0.2.5.dist-info/RECORD
