Metadata-Version: 2.2
Name: hdf5view
Version: 0.2.5
Summary: hdf5view is a python based HDF5 file viewer built on PyQt5/PySide2/PyQt6/PySide6, QtPy, h5py and pyqtgraph.
Author: Martin Swarbrick, Thomas G. Woodcock, The hdf5view Developers
Maintainer: Thomas G. Woodcock
License: MIT License
Project-URL: Documentation, https://tgwoodcock.github.io/hdf5view
Project-URL: Source, https://github.com/tgwoodcock/hdf5view/
Project-URL: Bug Tracker, https://github.com/tgwoodcock/hdf5view/issues
Project-URL: Changelog, https://github.com/tgwoodcock/hdf5view/blob/main/CHANGELOG.rst
Keywords: research,data,management,visualization,hdf5,viewer
Classifier: Programming Language :: Python
Classifier: Programming Language :: Python :: 3
Classifier: Development Status :: 3 - Alpha
Classifier: Environment :: X11 Applications :: Qt
Classifier: Intended Audience :: End Users/Desktop
Classifier: Intended Audience :: Science/Research
Classifier: License :: OSI Approved :: MIT License
Classifier: Operating System :: POSIX
Classifier: Operating System :: Microsoft :: Windows
Classifier: Operating System :: MacOS
Classifier: Topic :: Software Development
Classifier: Topic :: Scientific/Engineering :: Visualization
Requires-Python: >=3.6
License-File: LICENSE
Requires-Dist: h5py
Requires-Dist: qtpy
Requires-Dist: psutil
Requires-Dist: pyqtgraph
Provides-Extra: doc
Requires-Dist: matplotlib; extra == "doc"
Requires-Dist: nbsphinx>=0.7; extra == "doc"
Requires-Dist: numpydoc; extra == "doc"
Requires-Dist: pydata-sphinx-theme; extra == "doc"
Requires-Dist: sphinx>=3.0.2; extra == "doc"
Requires-Dist: sphinx-codeautolink[ipython]<0.14; extra == "doc"
Requires-Dist: sphinx-copybutton>=0.2.5; extra == "doc"
Requires-Dist: sphinx-design; extra == "doc"
Provides-Extra: tests
Requires-Dist: numpydoc; extra == "tests"
Requires-Dist: pytest>=5.4; extra == "tests"
Requires-Dist: pytest-benchmark; extra == "tests"
Requires-Dist: pytest-rerunfailures; extra == "tests"
Requires-Dist: pytest-xdist; extra == "tests"
Requires-Dist: pytest-qt; extra == "tests"
Provides-Extra: coverage
Requires-Dist: coverage>=5.0; extra == "coverage"
Requires-Dist: pytest-cov>=2.8.1; extra == "coverage"
Provides-Extra: dev
Requires-Dist: ruff; extra == "dev"
Requires-Dist: pre-commit>=1.16; extra == "dev"
Requires-Dist: hdf5view[coverage,doc,tests]; extra == "dev"
